careless/__init__.py
careless/_summary.py
careless/_validation.py
careless/evenodd.py
careless/irv.py
careless/longstring.py
careless/mahad.py
careless/psychsyn.py
careless_py-1.0.4.dist-info/licenses/LICENSE
careless_py-1.0.4.dist-info/METADATA
careless_py-1.0.4.dist-info/WHEEL
careless_py-1.0.4.dist-info/top_level.txt
careless_py-1.0.4.dist-info/RECORD
