Metadata-Version: 2.4
Name: careless-py
Version: 1.0.4
Summary: Python version of R careless package
Author-email: Cameron Lyons <cameron.lyons2@gmail.com>
Project-URL: Homepage, https://github.com/Cameron-Lyons/careless-py
Project-URL: Bug Tracker, https://github.com/Cameron-Lyons/careless-py/issues
Classifier: Programming Language :: Python :: 3
Classifier: License :: OSI Approved :: MIT License
Classifier: Operating System :: OS Independent
Requires-Python: >=3.10
License-File: LICENSE
Requires-Dist: numpy>=1.17.0
Provides-Extra: full
Requires-Dist: scipy>=1.0.0; extra == "full"
Provides-Extra: dev
Requires-Dist: scipy>=1.0.0; extra == "dev"
Requires-Dist: pytest>=6.0.0; extra == "dev"
Requires-Dist: pytest-cov>=2.0.0; extra == "dev"
Requires-Dist: mypy>=0.900; extra == "dev"
Requires-Dist: ruff>=0.1.0; extra == "dev"
Requires-Dist: pylint>=2.0.0; extra == "dev"
Requires-Dist: bandit>=1.6.0; extra == "dev"
Requires-Dist: pip-audit>=1.0.0; extra == "dev"
Requires-Dist: hypothesis>=6.0.0; extra == "dev"
Dynamic: license-file
